{
    "song_details": {
        "name": "Dehi Tava Pada",
        "raga": "Sahana",
        "arohanam": "S R2 G3 M1 P M1 D2 N2 S ||",
        "avarohanam": "S N2 D2 P M1 G3 M1 R2 G3 R2 S ||",
        "tala": "Adi",
        "composer": "Tyagaraja",
        "compositionType": "Kriti"
    },
    "composition": [
        {
            "section": "Pallavi",
            "content": [
                {
                    "swara": "; rg      gr - R      ; rg       , m P    |   Pdp M          mg gm  |  , R ,        ; ;     ||",
                    "sahitya": "De-    - -   Hi      -Tava    - Pada      Bha- -            Ktim - -     - - -        - - ||"
                },
                {
                    "swara": "; rg      gr - R      ; rg       , m P    |   Pdp M          mg gm  |  R-Rgr      S-rs   ||",
                    "sahitya": "De-    - -   Hi      -Tava    - Pada      Bha- -            Ktim - -     - - -          - Vai- ||"
                },
                {
                    "swara": "ns- rg      gr - R      ; rg       , m P    |   Pdp M          mg gm  |  R-Rgr      S-rs   ||",
                    "sahitya": "De-      - -   Hi      -Tava    - Pada      Bha- -            Ktim - -     - - -          - Vai- ||"
                },
                {
                    "swara": "ns- rg      gr - R      ; rg       , m P    |   MpDpM       mg gm  |  R-   gr      S-rs   ||",
                    "sahitya": "De-      - -   Hi      -Tava    - Pada      Bha- -            Ktim - -     - - -          - Vai- ||"
                },
                {
                    "swara": "ns- rg      gr - R      ; rn       , d P    |   Pdp M            mg gm  |  R-   gr      S-rs   ||",
                    "sahitya": "De-      - -   Hi      -Tava    - Pada      Bha- -            Ktim - -     - - -          - Vai- ||"
                },
                {
                    "swara": "ns- rg      gr - R      ; rn       , d P    |    rgmp            d N dp | M ;   Mpm    gm-rs   ||",
                    "sahitya": "De-      - -   Hi      -Tava    - Pada      Bha- -            - -  Ktim - -     - - -      - - Vai- ||"
                },
                {
                    "swara": "S mg rs     ; - sr  SD D     nS d  | ns R      ;  ;  |    ;  ;            ;  ns  ||",
                    "sahitya": "De - -Hi     -   Pa-  Ti - Ta    Pa- -        Va- Ni         -  -         -    -              -  Vai ||"
                },
                {
                    "swara": "S mg rs     ; - sr  rsD D     nS d  | ns R      rgmp |    ndpm           gmrs  ||",
                    "sahitya": "De - -Hi     -   Pa-  Ti - Ta      Pa- -       Va- Ni         Me -      Sa - -           Da - - ||"
                },
                {
                    "swara": "ns-  S      mg rs - sr    rsD D     nS d  | ns R      rgmp |    ndpm           gmrs  ||",
                    "sahitya": "Vai-de -  Hi     -   Pa-  Ti - Ta     Pa- -  Va- Ni         Me -      Sa - -           Da - - ||"
                },
                {
                    "swara": "ns- rg      gr - R      ; rn       , d P    |    rgmp            D rsN |  dpM  Mpm    gm-rs   ||",
                    "sahitya": "Vai De-    - -   Hi      -Tava    - Pada      Bha- -            - -  -  -   Ktim  - - -      - - Vai- ||"
                },
                {
                    "swara": "S mg rs     ; - sr  rsD D     nS d  | ns R      rgmp |    ndpm           gmrs  ||",
                    "sahitya": "De - -Hi     -   Pa-  Ti - Ta      Pa- -       Va- Ni         Me -      Sa - -           Da - - ||"
                },
                {
                    "swara": "ns- rg      gr - R         ; ;         ; ;     |    ;  rn      ,d P    |   ; M             P  ;    ||",
                    "sahitya": "Vai De-    - -   Hi         - -        - -          -  Tava    - Pada        Bha           Ktim ||"
                }
            ]
        },
        {
            "section": "Anupallavi",
            "content": [
                {
                    "swara": "; nd   N , dp        M , - d    , n    S   |   ;   N          , R ,   |  S ;          ;  ;  ||",
                    "sahitya": "Ai-  Hi - Ka       - -    Mu -Shmika    -   Pha      - La -     De-          - - ||"
                },
                {
                    "swara": "; nd   N , dp        M , - d    , n    S   |   ;   N          , R ,   |  S ;          sr ns  ||",
                    "sahitya": "Ai-  Hi - Ka       - -    Mu -Shmika    -   Pha      - La -     De-          - - ||"
                },
                {
                    "swara": "D-nd   N , dp        M , - d    , n    S   |   ;   N          , R ,   |  S ,r         sr ns  ||",
                    "sahitya": "Ai-  Hi - Ka       - -    Mu -Shmika    -   Pha      - La -     De-          - - ||"
                },
                {
                    "swara": "D-nd   rsN , dp        M , - d    , n    S   |   ;   N         , R ,   |  srsr         sr ns  ||",
                    "sahitya": "Ai-   Hi -  Ka       - -    Mu -Shmika      -   Pha       - La -     De-          - - ||"
                },
                {
                    "swara": "D-nd   rsN , dp        M , - d    , n    S   |   ;   ns         rgM   |  mgm-r      gr S  ||",
                    "sahitya": "Ai-   Hi -  Ka       - -    Mu -Shmika      -   Pha      La - -     De-  - -       - - - ||"
                },
                {
                    "swara": "; R  S Srs   N dn    n S d  |   dnD  P      Pdp M   |  mp gm   rg gr  ||",
                    "sahitya": "Ka        Ma La-     -  Sa-     Na-nan      Nya-  Ja      Va-   Ra     Ja-  Na-   Ni - - ||"
                },
                {
                    "swara": "S- R  S Srs   N dn    n S d  |   dnD  P      Pdp M   |  Mpm gm   rg gr  ||",
                    "sahitya": "Ka      Ma La-     -  Sa-     Na-nan      Nya-  Ja      Va-   Ra     Ja-  -  Na-   Ni - ||"
                },
                {
                    "swara": "S- R  S Srs   N dn    n S d  |   dnD  P      Pdp M   |  Mpm gm   Rgr S  ||",
                    "sahitya": "Ka      Ma La-     -  Sa-     Na-nan      Nya-  Ja      Va-   Ra     Ja-  -  Na-   Ni - ||"
                },
                {
                    "swara": "; - R  S Srs   N dn    n S d  |   dnD  P      rgmp   |   nd pm   gm rs  ||",
                    "sahitya": "Ka      Ma La-     -  Sa-     Na-nan      Nya-  Ja      Va-ra-     Ja- Na-   Ni - ||"
                },
                {
                    "swara": "ns- rg      gr - R      ; rn       , d P    |    rgmp            D rsN |  dpM  Mpm    gm-rs   ||",
                    "sahitya": "Vai De-    - -   Hi      -Tava    - Pada      Bha- -            - -  -  -   Ktim  - - -      - - Vai- ||"
                },
                {
                    "swara": "S mg rs     ; - sr  rsD D     nS d  | ns R      rgmp |    ndpm           gmrs  ||",
                    "sahitya": "De - -Hi     -   Pa-  Ti - Ta      Pa- -       Va- Ni         Me -      Sa - -           Da - - ||"
                },
                {
                    "swara": "ns- rg      gr - R         ; ;         ; ;     |    ;  rn      ,d P    |   ; M             P  ;    ||",
                    "sahitya": "Vai De-    - -   Hi         - -        - -          -  Tava    - Pada        Bha           Ktim ||"
                }
            ]
        },
        {
            "section": "Charanam",
            "content": [
                {
                    "swara": "; pp  , P ,  P P  ; ;  | ; ;     ;  ;  |    ;  ;       ; ;   ||",
                    "sahitya": "Sara       Na        Gata ||"
                },
                {
                    "swara": "; pp  , P ,  P rg  mp-rg   |  mp-dn     , dpM , |   mgmr     gr S  ||",
                    "sahitya": "Sara       Na        Gata        - -   - -       - -   Pa-   - - -         La- - -     Ne - - ||"
                },
                {
                    "swara": "; pp  , P ,  pr- rg  mp-rg   |  mp-drsn   , dpM , |   Mpm gm rg gr ||",
                    "sahitya": "Sara       Na        Ga-ta      - -   - -       - -   Pa-     - - -         La- - -      Ne - - ||"
                },
                {
                    "swara": "S- pp  , P ,  pr- rg  mp-Dnd  |  pm- Mpm  mgM  |   rg gr      S ;  ||",
                    "sahitya": "Sara       Na      Ga-ta      - -   - -  -     - -   Pa-     --  La-    Ne - -      - - ||"
                },
                {
                    "swara": "; N  , smg      rs- sn     dN - dp | M  - nd      N  ;  | sn sr    , S  ,   ||",
                    "sahitya": "Sha       - Ta -       Mu Kha   Ma-  Da-   -     Da-     Ma -    Ne- -       - - - ||"
                },
                {
                    "swara": "; nd     , P ,       pd -mp     , p  M   |   ;   D          , N ,   |  S ;          ;  ;  ||",
                    "sahitya": "Taru   Na      Ru-  Na-   -Bja -       -   Na         - Ya -      Ne         - - ||"
                },
                {
                    "swara": "; nd     , P ,       pd -mp     , p  M   |   ;   nd          , N ,   |  S ;          ;  ;  ||",
                    "sahitya": "Taru   Na      Ru-  Na-   -Bja -       -   Na         - Ya -      Ne         - - ||"
                },
                {
                    "swara": "; nd     , P ,       pd -mp     , p  M   |   ;   nd          , N ,   |  S ,r        srns  ||",
                    "sahitya": "Taru   Na      Ru-  Na-   -Bja -       -   Na         - Ya -      Ne         - - ||"
                },
                {
                    "swara": "D- nd     dN dp   M; - D      D ,n    |   S-   N          , R ,   |  S ,r        srns  ||",
                    "sahitya": "Ta-     Ru  Na    -    Ru     Na-       Bja-  Na        - Ya -     Ne         - - ||"
                },
                {
                    "swara": "D- nd     rsN; dp   M; - D      D ,n    |   S-   N          , R ,   |  srsr        srns  ||",
                    "sahitya": "Ta-     Ru  Na    -     Ru      Na-       Bja-  Na        - Ya -     Ne         - - ||"
                },
                {
                    "swara": "D- nd     rsN; dp   M; - D      D ,n    |   S-   ns          rgM   |  mgm-r      gr-S  ||",
                    "sahitya": "Ta-     Ru  Na    -     Ru      Na-       Bja-  Na         Ya - -    Ne   - -       -  - - ||"
                },
                {
                    "swara": "; R  S  Srs   N dn    n S d  |   dnD  P      Pdp M   |  mp gm   Rgr S   ||",
                    "sahitya": "Tya      Ga Ra-     -  - -       Ja -  -          Hrt-  -      Sa-  Da      Ne -  - -   -  -  - ||"
                },
                {
                    "swara": "; R  S  Srs   N dn    n S d  |   dnD  P      Pdp M   |  mgmr    gr S   ||",
                    "sahitya": "Tya      Ga Ra-     -  - -       Ja -  -          Hrt-  -      Sa-  Da      Ne -  - -   -  -  - ||"
                },
                {
                    "swara": "; R  S  Srs   N dn    n S d  |   dnD  pr     rg mp   |   ndpm    gmrs   ||",
                    "sahitya": "Tya      Ga Ra-     -  - -       Ja -  -          Hrt-  -      Sa-  Da      Ne -  - -   -  -  - ||"
                },
                {
                    "swara": "ns- rg      gr - R      ; rn       , d P    |    rgmp            D rsN |  dpM  Mpm    gm-rs   ||",
                    "sahitya": "Vai De-    - -   Hi      -Tava    - Pada      Bha- -            - -  -  -   Ktim  - - -      - - Vai- ||"
                },
                {
                    "swara": "S mg rs     ; - sr  rsD D     nS d  | ns R      rgmp |    ndpm           gmrs  ||",
                    "sahitya": "De - -Hi     -   Pa-  Ti - Ta      Pa- -       Va- Ni         Me -      Sa - -           Da - - ||"
                },
                {
                    "swara": "ns- rg      gr - R         ; ;         ; ;     |    ;  rn      ,d P    |   ; M             P  ;    ||",
                    "sahitya": "Vai De-    - -   Hi         - -        - -          -  Tava    - Pada        Bha           Ktim ||"
                }
            ]
        }
    ],
    "pdfPath": "PDFs/Dehi_Tava_Pada_Sahana.pdf",
    "avartanasPerRow": 1
}