{
    "song_details": {
        "name": "Kaligiyunte",
        "raga": "Keeravani",
        "arohanam": "S R2 G2 M1 P D1 N3 S ||",
        "avarohanam": "S N3 D1 P M1 G2 R2 S ||",
        "tala": "Adi",
        "composer": "Tyagaraja"
    },
    "sections": {
        "pallavi": [
            {
                "line_number": 1,
                "swara": "- - - sg rs - n S nS R- - - G R G - | gr R- - gR gM - | R - G - - - Rgr ||",
                "sahitya": "- - - Ka li - - gi-yun te Kaa- - daa- - Gal- - - - gu - - - nu- -"
            },
            {
                "line_number": 2,
                "swara": "RS S rg rsS n S nS R- - - G R G - | gr R- - gR gM - | R - G - - - rgmg ||",
                "sahitya": "- - -ka-- li - - - gi-yun te Kaa- - daa- - Gal- - - - gu - - - nu- -"
            },
            {
                "line_number": 3,
                "swara": "grrs S rg rsS n S nS R- - - dg R G - | gr R- - gR gM - | R - Mpm G - Mpd pm ||",
                "sahitya": "- - -ka-- li - - - gi-yun te Kaa- - daa- - Gal- - - - gu - - - nu- -"
            },
            {
                "line_number": 4,
                "swara": "grsn S- R - g MP- D P DP P - - - | - - Pdp P - M - | G - - - - - Mpm ||",
                "sahitya": "- - - - Kaa - mi tha Pha-la- - daa- -- - - - - - - - ya- kaa-- - - - - - - -"
            },
            {
                "line_number": 5,
                "swara": "GRS - R - g MP- D P DP dPd N- | - - Dnr sn D P- | P Pdp M Mpm G - mpD pm ||",
                "sahitya": "- - - - Kaa - mi tha Pha-la- - daa- -- - - - - - - - ya- kaa-- - - - - - - - - - - - - - - - -"
            },
            {
                "line_number": 6,
                "swara": "grsn S- R - g MP- D P DP dPd ns R | S - Dnr sn D P- | P mpdp M gmpm G - mpD pm ||",
                "sahitya": "- - - - Kaa - mi tha Pha-la- - daa- -- - - - - - - - ya- kaa-- - - - - - - - - - - - - - - - -"
            },
            {
                "line_number": 7,
                "swara": "grsn",
                "sahitya": "----"
            }
        ],
        "anupallavi": [
            {
                "line_number": 1,
                "swara": "- - - P D P N - S - sn D - dr r r sn | S - - P G R G - | M - mg G - G R- ||",
                "sahitya": "- - - Ka li ni yin ke- tha-- - Me-ru--- - - - ga ka - Nin- naa- du- - - Konti"
            },
            {
                "line_number": 2,
                "swara": "- - S S N D D N S - sn D - dr r r sn | S - - P G R G - | M - mg G - G R- ||",
                "sahitya": "- - - Ka li ni yin ke- tha-- - Me-ru--- - - - ga ka - Nin- naa- du- - - Konti"
            },
            {
                "line_number": 3,
                "swara": "- - S sn rs n D D- pdns Rgr sn D- pr srgr sn | S - - P G R G - | mg P mgG - - G R- ||",
                "sahitya": "- - - Ka li ni - yin- ke- tha-- - Me-ru--- - - - ga ka - Nin- naa-- du- - - Konti"
            },
            {
                "line_number": 4,
                "swara": "- - - S S S nsrs - r sn D D - dPd N - | - - Dnr sn D P - | P dp M pm G - gr R ||",
                "sahitya": "- - Cha lamu Se--- - ya-- ka - Na—tha- - - lanu- - - - Cha- kka-- ni- - Vra- - - -"
            },
            {
                "line_number": 5,
                "swara": "S - - S S S nsrs - r sn D D - dPd ns R | S - Dnr sn D P - | P mpdp M gmpm G - Mpd pm ||",
                "sahitya": "tha - Cha lamu Se--- - ya-- ka - Na—tha- - - lanu- - - - Cha- kka-- - - ni- - - - Vra- - - -"
            },
            {
                "line_number": 6,
                "swara": "grsn",
                "sahitya": "tha -- (kaligiyunte)"
            }
        ],
        "charanams": [
            {
                "lines": [
                    {
                        "line_number": 1,
                        "swara": "- - - P - P P - Mpm mg - G - gr R | - - - S R G R - | G - gm pm G G gr sn ||",
                        "sahitya": "- -- Bha - ga va tha- - - - - - - Gre-- - - - sa ru la ku Na- - - - - - - - ra dha- - -"
                    },
                    {
                        "line_number": 2,
                        "swara": "s R g M- P - P P - Mpm mggmpd N D P G | R - - S R G R - | G - gm pm G G gr sn ||",
                        "sahitya": "- -- Bha - ga va tha- - - - - - - - - - Gre- - - - sa ru la ku Na- - - - - - -- - ra dha- - -"
                    },
                    {
                        "line_number": 3,
                        "swara": "S - G R G - M - P - - D P - d N - | - - D nr sn D P - | Pdp Mpm G - gr R ||",
                        "sahitya": "- - Pra- hlaa- - - da - - Pa raa- - sha- - - ra - - - - - Ra- ma- daa- - su- lu - -"
                    },
                    {
                        "line_number": 4,
                        "swara": "S - - P dp P D - ns - sn D - pr rrsn | S - - P G R G - | M - mg G - G R - ||",
                        "sahitya": "- - - Bhaa- - gu ga Sri- - - - Ra-ghu-- - - - raa - muni- Paa da- - - Mula"
                    },
                    {
                        "line_number": 5,
                        "swara": "- - - S - S S - nsrs -r sn D dPd N - | - - Dnr sn D P - | Pdp Mpm G - gr R - ||",
                        "sahitya": "- - - Bha - kti Je si- - - na- - Ree thi- - - - Tya- ga-- ra ju- - ni- - ki - pu - -"
                    },
                    {
                        "line_number": 6,
                        "swara": "S - - S - S S nsrs - r sn D dPd ns R | S - Dnr sn D P - | P mpdp M gmpm G - Mpd pm ||",
                        "sahitya": "du - -bha- kti Je si- - - na- - Ree thi- - - - Tya- ga-- ra ju- -- - ni- -- - - - ki - pu - -"
                    },
                    {
                        "line_number": 7,
                        "swara": "grsn",
                        "sahitya": "du -- (kaligiyunte)"
                    }
                ]
            }
        ]
    },
    "pdfPath": "PDFs/Kaligiyunte_Keeravani.pdf"
}