{
    "song_details": {
        "name": "Krupaya Paalaya",
        "raga": "Charukesi",
        "arohanam": "S R2 G3 M1 P D1 N2 S ||",
        "avarohanam": "S N2 D1 P M1 G3 R2 S ||",
        "tala": "Triputa",
        "composer": "Swati Tirunal",
        "compositionType": "Kriti"
    },
    "composition": [
        {
            "section": "Pallavi",
            "content": [
                {
                    "swara": ";  P   M  | m g g r      S , r  ||   G , M ,    |    p d p d  M P  ||",
                    "sahitya": "Krupa   Ya - - -      Paa-       La - Ya-        Shau- -  Re!- ||"
                },
                {
                    "swara": "gm-  P   M  | m g g r     S , r     ||   G , M ,    |    p d n d     p m g r   ||",
                    "sahitya": "- -   Krupa     Ya - - -     Paa-         La - Ya-        Shau- -     Re!- ||"
                },
                {
                    "swara": "gm-  P   M  | m g g r     S , r     ||   G , M ,    |    p d n s     n d p m    ||",
                    "sahitya": "- -   Krupa     Ya - - -     Paa-         La - Ya-        Shau- -     Re!- ||"
                },
                {
                    "swara": "gm-  P   M  | m g g r     S , r     ||   G , M ,    |    p d n s     r s n d ||",
                    "sahitya": "- -   Krupa     Ya - - -     Paa-         La - Ya-        Shau- -     Re!- ||"
                },
                {
                    "swara": "p m - G M   | p D p    d n  S      || d n s R s   | n s n d  p m g r  ||",
                    "sahitya": "- -     Karu     Naa--     Ra- - -        Saa- - - -      Vaa- - -  - - - - - ||"
                },
                {
                    "swara": "g m- P   M  | m g g r     S ;       ||  n r s D ,     | N ;  S ;  ||",
                    "sahitya": "La!-   Ka Lu   Shaa- -       Rtthi      Vi - -  -  --      Raa-  Ma! ||"
                },
                {
                    "swara": ";   ;   ;       |   ;  , d      p m g r    ||  s r g m p d  | n s n d     p m g r   ||",
                    "sahitya": "-   -   -           -  - Paa -  - - - -        Hi- - -  - - -   Shau- -    Re !- - - ||"
                }
            ]
        },
        {
            "section": "Anupallavi",
            "content": [
                {
                    "swara": "; P D  |  N D     D  N  ||  S , S ,  | n s  R  S ;  || d n S ,- p  |  d n S    , - s n d  ||",
                    "sahitya": "Tapa    Nee-     Ya  -     Ni  Bha Che- -   La!    - -  - - -        - - - -    - - - - - ||"
                },
                {
                    "swara": "pm- P D   |  N D     D  N  ||  S , S ,  | n s  R  S ;  || p d n s R  |  S ,  n   -  r  s n d  ||",
                    "sahitya": "- -   Tapa     Nee-     Ya  -     Ni  Bha Che- -   La!    - -  - - -        - - - -    - - - - - ||"
                },
                {
                    "swara": "pm- P D   |  nsR ;,g  rsnd ; ,n ||  S , S ,   | n s  R   S ;  || r g m g g r  |  r s s n   -  n d d p   ||",
                    "sahitya": "- -   Tapa     Nee-      Ya  -         Ni  Bha  Che- -   La!    - -  - - -        - - - -    - - - - - ||"
                },
                {
                    "swara": "pm- P D   |  nsR ;,g  rsnd ; ,n ||  S , S ,   | n s  R   S ;  || ;  G G    |  r g m g     g r S    ||",
                    "sahitya": "- -   Tapa     Nee-      Ya  -         Ni  Bha  Che- -   La!      Tu Hi      Naa- - -     - - Mshu ||"
                },
                {
                    "swara": "n r s D ,    |   N ;  S ;  ||  ; S R  |   G  ;    G ;  ||  m g R S  |  n d D       n s R  ||",
                    "sahitya": "Su-- Va-        Da-  Na!     - Sri-      Pa-    Dma-      Naa- - -      Bha!- -      - - - ||"
                },
                {
                    "swara": "S - n s n r  | s n D    P , m ||   p d n s   r g |  r s n d  p m g r || g m",
                    "sahitya": "-    Sa-ra-     Si- -     Ja- -      Lo-  - - -  -     Cha- -  Na!- - -    - -    (Krupayapaalaya) ||"
                }
            ]
        },
        {
            "section": "Charanam",
            "content": [
                {
                    "swara": "; S R  | G ;    M G  || m g R S       |  s n r s  n d D  ||",
                    "sahitya": "Kuru   Me Kusha   Lam - -  -         Mu- -   Daa - - ||"
                },
                {
                    "swara": ";  P D  |  N D  D  N  ||  S ,  S ,         |  s r g m  G  ;  ||",
                    "sahitya": "Kuru   Vin -     Da   -      Ni  Bha          Dan- - -       Ta!- ||"
                },
                {
                    "swara": "; P M  | m g g r    S ;  || S  ;   ;           | s r Gm g       R S  ||",
                    "sahitya": "Niru   Pa- - -     Ma-    Sam -  -          Saa- - - -       -  Ra ||"
                },
                {
                    "swara": "; n s n r  |  s n  D     D N  ||  s R g M       |  p d p d  M P  ||",
                    "sahitya": "Ni- - -     Ra-  -      Dhi -     Va- Ra -           Po - - -  Ta! ||"
                },
                {
                    "swara": "; P D  |  N D     D  N  ||  S , S ,  | n s  R  S ;  || d n S ,- p  |  d n S    , - s n d  ||",
                    "sahitya": "Naa-     Rada     Mu -          - - Kha  Mu- -    Ni-      -  - - -  -      - - - -    - - - - ||"
                },
                {
                    "swara": "pm- P D   |  N D     D  N  ||  S , S ,  | n s  R  S ;  || p d n s R  |  S ,  n   -  r  s n d  ||",
                    "sahitya": "Naa-     Rada     Mu -       - - Kha  Mu- -    Ni-      -  - - -  -      - - - -    - - - - ||"
                },
                {
                    "swara": "pm- P D   |  nsR ;,g  rsnd ; ,n ||  S , S ,   | n s  R   S ;  || r g m g g r  |  r s s n   -  n d d p   ||",
                    "sahitya": "Naa-     Ra-   -    Da - - - -    Mu Kha  Mu- -    Ni-      -  - - -  -          - - - -    - - - - ||"
                },
                {
                    "swara": "pm- P D   |  nsR ;,g  rsnd ; ,n ||  S , S ,   | n s  R   S ;  || ;  G G    |  r g m g     g r S    ||",
                    "sahitya": "Naa-     Ra-   -    Da - - - -    Mu Kha  Mu- -    Ni-       Ni Ka      Ra - - -       -  - - ||"
                },
                {
                    "swara": "n r s -D ,    |   D N   S ;  ||  ; S    R  |   G  ;    G ;  ||  m g R S  |  n d D       n s R  ||",
                    "sahitya": "Ge-- Ya -      Chari   Ta!      Vaa Ra      Ya-    Maam      A -  -  -      Khi- -       La - - ||"
                },
                {
                    "swara": "S - n s n r  | s n D    P d m ||   p d n s   r g |  r   s n d  p m g r || g m",
                    "sahitya": "-   Paa- -     Pa- -    Jaa   -        Tam-  -  - - -   Bha-ga-  Van!- -     - -    (Krupayapaalaya) ||"
                }
            ]
        }
    ],
    "pdfPath": "PDFs/Krupaya_Paalaya_Charukesi.pdf",
    "avartanasPerRow": 2
}